Workbook
Name BaseUnits: [1]Assumptions!$C$7
Name FixedCosts: [1]Assumptions!$C$8
Name Price: [1]Assumptions!$C$5
Name TaxRate: [1]Assumptions!$C$9
Name VarCost: [1]Assumptions!$C$6

Sheet Score Sheet
A1: MIS 445: Advanced Data Visualization and Spreadsheet Modelling (Summer - 2026) Mid Exam Marks: 30 Time: 1 h 30 Min Date: July 30, 2026
A2: MIDTERM EXAMINATION MARKING SHEET
B4: Student Name: | D4: Student ID: | F4: Total : | G4: =D45
B6: Part & Task Description | C6: Max Marks | D6: Score
A7: Question 1 | C7: 10
B8: a | C8: 2 | D8: ='Question 1'!T2
B9: b | C9: 2 | D9: ='Question 1'!T8
B10: c | C10: 2 | D10: ='Question 1'!T14
B11: d | C11: 2 | D11: ='Question 1'!T19
B12: e | C12: 2 | D12: ='Question 1'!T24
A13: Q1 Subtotal /10 | D13: =SUM(D8,D9,D10,D11,D12)
A15: Question 2 | C15: 10
B16: a | C16: 1 | D16: ='Question 2'!O4
B17: b | C17: 4 | D17: ='Question 2'!O7
B18: c | C18: 2 | D18: ='Question 2'!O10
B19: d | C19: 3 | D19: ='Question 2'!O13
A20: Q2 Subtotal /10 | D20: =SUM(D16,D17,D18,D19)
A22: Question 3 | C22: 10
B23: a | C23: 1 | D23: ='Question 3'!T4
B24: b | C24: 2 | D24: ='Question 3'!T7
B25: c | C25: 2 | D25: ='Question 3'!T10
B26: d | C26: 2 | D26: ='Question 3'!T13
B27: e | C27: 3 | D27: ='Question 3'!T16
A28: Q3 Subtotal /10 | D28: =SUM(D23,D24,D25,D26,D27)
A30: Question 4 | C30: 10
B31: a | C31: 2 | D31: ='Question 4'!V4
B32: b | C32: 3 | D32: ='Question 4'!V7
B33: c | C33: 5 | D33: ='Question 4'!V10
A34: Q4 Subtotal /10 | D34: =SUM(D31,D32,D33)
A36: Question 5 | C36: 10
B37: a | C37: 2 | D37: ='Question 5'!V4
B38: b | C38: 2 | D38: ='Question 5'!V7
B39: c | C39: 2 | D39: ='Question 5'!V10
B40: d | C40: 2 | D40: ='Question 5'!V13
B41: e | C41: 2 | D41: ='Question 5'!V16
A42: Q5 Subtotal /10 | D42: =SUM(D37,D38,D39,D40,D41)
A45: FINAL SCORE (Any 3 of 5) | D45: =SUM(D42,D34,D28,D20,D13)
A46: OUT OF | D46: 30

Sheet Instructions
A2: Exam Instructions – MIS445 (Excel Exam)
A3: Total time: 1 hour 30 minutes (inclusive of submission)
A5: Please read all instructions carefully.
A6: 1. Getting the Exam File
A7: Get the Exam File.
A8: Use Save as on the exam file and save to your Desktop.
A9: Use the following naming convention:
A10: firstname_ID_MIS445_sectionNo.xlsx
A11: (Example: Ayesha_22101567_MIS445_3.xlsx)
A13: 2. Answering the Questions
A14: You must answer any three (3) questions from the exam.
A15: You may use separate sheets for different questions.
... A28: When the exam ends, follow your instructions given by the instructor for submission.

Sheet Question 1
A1: CITY based Card expenditure | Used for: Q1 | K1: Remember: Answer these questions by creating PivotTable and appropriate PivotCharts
A2: index | B2: City | C2: Date | D2: Card Type | E2: Exp Type | F2: Gender | G2: Amount | S2: Score:
A3: 0 | B3: Delhi, India | C3: 41941 | D3: Gold | E3: Bills | F3: F | G3: 82475 | K3: Q1. (2 pts) | L3: CLO4
A4: 1 | B4: Greater Mumbai, India | C4: 41873 | D4: Platinum | E4: Bills | F4: F | G4: 32555 | I4: Delhi, India | K4: Which city had the highest total spending?
A5: 2 | B5: Bengaluru, India | C5: 41878 | D5: Silver | E5: Bills | F5: F | G5: 101738 | K5: Answer space: _______________________________________
A6: 3 | B6: Greater Mumbai, India | C6: 41741 | D6: Signature | E6: Bills | F6: F | G6: 123424
A7: 4 | B7: Bengaluru, India | C7: 42129 | D7: Gold | E7: Bills | F7: F | G7: 171574
A8: 5 | B8: Delhi, India | C8: 41890 | D8: Silver | E8: Bills | F8: F | G8: 100036 | K8: Q2. (2 pts) | L8: CLO4 | S8: Score:
A9: 6 | B9: Delhi, India | C9: 42059 | D9: Gold | E9: Bills | F9: F | G9: 143250 | I9: Female (F) | K9: Which gender uses Platinum cards more?
A10: 7 | B10: Greater Mumbai, India | C10: 41816 | D10: Platinum | E10: Bills | F10: F | G10: 150980 | K10: Answer space: _______________________________________
A11: 8 | B11: Delhi, India | C11: 41726 | D11: Silver | E11: Bills | F11: F | G11: 192247
A12: 9 | B12: Delhi, India | C12: 41883 | D12: Platinum | E12: Bills | F12: F | G12: 67932
A13: 10 | B13: Delhi, India | C13: 41812 | D13: Platinum | E13: Bills | F13: F | G13: 280061 | K13: Q3. (2 pts) | L13: CLO4
A14: 11 | B14: Greater Mumbai, India | C14: 41615 | D14: Signature | E14: Bills | F14: F | G14: 278036 | I14: No Fuel expenditure in this dataset | K14: Which city spends the most on Fuel? | S14: Score:
A15: 12 | B15: Greater Mumbai, India | C15: 41858 | D15: Gold | E15: Bills | F15: F | G15: 19226 | K15: Answer space: _______________________________________
A16: 13 | B16: Delhi, India | C16: 41756 | D16: Signature | E16: Bills | F16: F | G16: 254359
A17: 14 | B17: Greater Mumbai, India | C17: 41866 | D17: Signature | E17: Bills | F17: F | G17: 302834 | J17: Note for Validation: The answers above are calculated using Python logic.
A18: 15 | B18: Greater Mumbai, India | C18: 41971 | D18: Platinum | E18: Bills | F18: F | G18: 647116 | J18: To fulfill the requirement natively, highlight B1:G14, click Insert > PivotTable. | K18: Q4. (2 pts) | L18: CLO4
A19: 16 | B19: Greater Mumbai, India | C19: 41804 | D19: Signature | E19: Bills | F19: F | G19: 421878 | J19: Add 'City' to Rows and 'Amount' to Values (for Q1). | K19: Which card type has the highest average transaction? | S19: Score:
A20: 17 | B20: Greater Mumbai, India | C20: 42093 | D20: Gold | E20: Bills | F20: F | G20: 986379 | K20: Answer space: _______________________________________
A21: 18 | B21: Greater Mumbai, India | C21: 41713 | D21: Platinum | E21: Bills | F21: F | G21: 213047
A22: 19 | B22: Greater Mumbai, India | C22: 41587 | D22: Platinum | E22: Bills | F22: F | G22: 735566
A23: 20 | B23: Delhi, India | C23: 41733 | D23: Signature | E23: Bills | F23: F | G23: 366102 | K23: Q5. (2 pts) | L23: CLO4
A24: 21 | B24: Delhi, India | C24: 41821 | D24: Signature | E24: Bills | F24: F | G24: 809623 | K24: Are there any expense types only used by males? | S24: Score:
A25: 22 | B25: Greater Mumbai, India | C25: 42090 | D25: Silver | E25: Bills | F25: F | G25: 467014 | K25: Answer space: _______________________________________
A26: 23 | B26: Ahmedabad, India | C26: 41558 | D26: Gold | E26: Bills | F26: F | G26: 668568
A27: 24 | B27: Ahmedabad, India | C27: 41724 | D27: Gold | E27: Bills | F27: F | G27: 339112
A28: 25 | B28: Delhi, India | C28: 41909 | D28: Silver | E28: Bills | F28: F | G28: 622170
A29: 26 | B29: Bengaluru, India | C29: 41721 | D29: Platinum | E29: Bills | F29: F | G29: 434427
A30: 27 | B30: Greater Mumbai, India | C30: 41776 | D30: Signature | E30: Bills | F30: F | G30: 655846
A31: 28 | B31: Bengaluru, India | C31: 42022 | D31: Platinum | E31: Bills | F31: F | G31: 987935
A32: 29 | B32: Delhi, India | C32: 42112 | D32: Gold | E32: Bills | F32: F | G32: 702774
A33: 30 | B33: Bengaluru, India | C33: 41851 | D33: Signature | E33: Bills | F33: F | G33: 225392
A34: 31 | B34: Greater Mumbai, India | C34: 42046 | D34: Gold | E34: Bills | F34: F | G34: 296573
A35: 32 | B35: Ahmedabad, India | C35: 41602 | D35: Platinum | E35: Bills | F35: F | G35: 227702
A36: 33 | B36: Ahmedabad, India | C36: 41951 | D36: Gold | E36: Bills | F36: F | G36: 864090
A37: 34 | B37: Ahmedabad, India | C37: 41888 | D37: Signature | E37: Bills | F37: F | G37: 440605
... A3843: 3840 | B3843: Bengaluru, India | C3843: 41895 | D3843: Platinum | E3843: Fuel | F3843: F | G3843: 52304

Sheet Question 2
A1: SunGuard Skincare Co. — Sunscreen | Used for: Q2 | G1: QUESTION 2 — [10 Marks]
A3: KEY INPUTS
A4: Selling price per unit ($) | B4: 18 | G4: (a) [1 pt] | H4: CLO2 | N4: Score:
A5: Variable cost per unit ($) | B5: 6.5 | G5: On a new sheet named 'Q2_WhatIf', create data data model to caclculate monthly profit by using the structure of the Monthly revenue model.
A6: Base units sold per month | B6: 2000
A7: Fixed costs per month ($) | B7: 12000 | G7: (b) [4 pts] | H7: CLO2 | N7: Score:
A8: Tax rate (%) | B8: 0.25 | G8: Build a Two-Variable Data Table showing Projected Net Profit when Units Increase % (rows: 0%, 5%, 10%, 15%, 20%, 25%, 30%) and Price Change % (columns: -20%, -10%, 0%, +10%, +20%) vary simultaneously.
G10: (c) [2 pts] | H10: CLO6 | N10: Score:
G11: Find the sales volume needed to achieve break-even.
G13: (d) [3 pts] | H13: CLO2 | N13: Score:
G14: In a few sentences, write a business interpretation of your Data Table from part (b) — what does it tell management about sensitivity to price increases? Write your answer directly in a text box or merged cell on Q2_WhatIf.
A15: Monthly Revenue Model
A17: OPERATING RESULTS
A18: Units sold
A19: Selling price per unit
A20: Revenue
A21: Variable cost per unit
A22: Total variable costs
A23: Contribution margin
A24: Fixed costs
A25: Earnings before tax (EBT)
A26: Tax rate
A27: Tax expense
... A29: Net profit margin (%)

Sheet Question 3
A1: AURORA REWARDS — Loyalty Customer Records (RAW EXPORT — UNCLEANED) | Used for: Q3 | L1: QUESTION 3 — [10 Marks]
L2: Business Context: Aurora Rewards' loyalty database was merged from the online store and two physical branches without standardisation. The membership team flagged serious data quality issues — names are inconsistently cased and spaced, join dates are in multiple formats, points balances contain errors, and emails/phone numbers are malformed. You are the Data Analyst tasked with auditing and cleaning the records before they enter the new CRM.
A4: CustomerID | B4: Full Name | C4: City | D4: Membership Tier | E4: Join Date | F4: Points Balance | G4: Email | H4: Phone | I4: Status | L4: (a) [1 pt] | M4: CLO1 | S4: Score:
A5: AU-7001 | B5: LIAM BIANCHI | C5: Portland | D5: Silver | E5: 44820 | F5: 771 | G5: liam.7001auroraliving.com | H5: 555-3323 | I5: Active | L5: Copy the dataset to a new sheet named 'Q3_Clean'. On the same sheet (or another sheet), create a Data Clean Summary box (a text box or table) that reports every step you took to complete the tasks below.
A6: AU-7002 | B6: Grace Patel | C6: Phoenix | D6: Platinum | E6: 45646 | F6: 4328 | G6: grace.7002@auroraliving.com | H6: 555-136-4116 | I6: Active
A7: AU-7003 | B7: AMINA BROWN | C7: Boston | D7: Platinum | E7: 45399 | F7: 4094 | G7: amina.7003@auroraliving.com | H7: 555-568-5557 | I7: Inactive | L7: (b) [2 pts] | M7: CLO1 | S7: Score:
A8: AU-7004 | B8: Grace Clarke | C8: Chicago | D8: Gold | E8: 44843 | G8: grace.7004@auroraliving.com | H8: N/A | I8: Active | L8: The Full Name column has multiple problems (inconsistent casing, leading/extra spaces). Fix them. Mention the steps in the Data Clean Summary.
A9: AU-7005 | B9: Maria Hassan | C9: Austin | D9: Bronze | E9: 44653 | F9: 3255 | G9: maria.7005auroraliving.com | H9: 555-679-4252 | I9: Suspended
A10: AU-7006 | B10: David Wong | C10: Chicago | D10: Gold | E10: 44767 | F10: -411 | G10: david.7006@auroraliving.com | H10: 555-161-8617 | I10: Inactive | L10: (c) [2 pts] | M10: CLO1 | S10: Score:
A11: AU-7007 | B11: Fatima Bianchi | C11: Portland | D11: Silver | E11: 45365 | F11: -265 | G11: fatima.7007@auroraliving.com | H11: 555-376-5983 | I11: Active | L11: Create a new phone number column where the phone number format is +1-(555)-136-4111. Any number that has less than 11 digits, mark them as invalid.
A12: AU-7008 | B12: PETER MALIK | C12: Denver | D12: Bronze | E12: 44666 | H12: 555-5854 | I12: Inactive
A13: AU-7009 | B13: Tom Clarke | C13: Miami | D13: Silver | E13: 44846 | F13: 1042 | H13: N/A | I13: Suspended | L13: (d) [2 pts] | M13: CLO1 | S13: Score:
A14: AU-7010 | B14: James Hassan | C14: Seattle | D14: Gold | E14: 44842 | F14: -372 | H14: +1-555-803-7360 | I14: Inactive | L14: The Join Date column contains different date formats. Fix them so every date uses a single, consistent format as follows - dd-mmm-yyyy (for example - 25 Jan 2026)
A15: AU-7011 | B15: AMINA CLARKE | C15: Austin | D15: Bronze | E15: 44578 | F15: 3208 | G15: amina7011auroralivingcom | H15: N/A | I15: Suspended
A16: AU-7012 | B16: Zainab Garcia | C16: Seattle | D16: Bronze | E16: 44667 | F16: 607 | G16: zainab7012auroralivingcom | H16: +1-555-308-1271 | I16: Active | L16: (e) [3 pt] | M16: CLO5 | S16: Score:
A17: AU-7013 | B17: DAVID ROSSI | C17: Miami | D17: Bronze | E17: 44630 | F17: 1077 | G17: david.7013@auroraliving.com | H17: 555-3267 | I17: Inactive | L17: Mention two other basic steps of data cleaning and apply on this dataset. At this point, would you recommend this data to be used ? Yes or No? Explain breifly.
A18: AU-7014 | B18: Chen Torres | C18: Seattle | D18: Bronze | E18: 44785 | F18: 174 | H18: 555-593-2102 | I18: Suspended
A19: AU-7015 | B19: Maria Wong | C19: Denver | D19: Bronze | E19: 45269 | F19: 1061 | G19: maria7015auroralivingcom | H19: 555-2391 | I19: Suspended
A20: AU-7016 | B20: ZAINAB CLARKE | C20: Austin | D20: Platinum | E20: 45311 | F20: 101 | H20: 555-182-2485 | I20: Suspended
A21: AU-7017 | B21: LINDA NGUYEN | C21: Boston | D21: Platinum | E21: 45645 | F21: 4433 | G21: linda.7017@auroraliving.com | H21: 555-417-2437 | I21: Inactive
A22: AU-7018 | B22: Michael Johnson | C22: Denver | D22: Platinum | E22: 45612 | F22: 3014 | G22: michael7018auroralivingcom | H22: +1-555-794-4318 | I22: Suspended
A23: AU-7019 | B23: Fatima Wong | C23: Portland | D23: Platinum | E23: 44725 | F23: 3529 | G23: fatima.7019@auroraliving.com | H23: +1-555-493-4597 | I23: Suspended
A24: AU-7020 | B24: Chen Adams | C24: Seattle | D24: Platinum | E24: 45314 | F24: 2267 | G24: chen.7020@auroraliving.com | H24: 555-561-8722 | I24: Inactive
A25: AU-7021 | B25: PETER ROSSI | C25: Portland | D25: Gold | E25: 45580 | G25: peter.7021@auroraliving.com | H25: 555-1679 | I25: Suspended
A26: AU-7022 | B26: david cohen | C26: Chicago | D26: Bronze | E26: 45364 | F26: 2182 | G26: david.7022@auroraliving.com | H26: +1-555-915-1769 | I26: Suspended
A27: AU-7023 | B27: Linda Murphy | C27: Boston | D27: Bronze | E27: 45389 | F27: 88 | G27: linda.7023auroraliving.com | H27: 555-283-4710 | I27: Inactive
A28: AU-7024 | B28: Priya Bianchi | C28: Seattle | D28: Platinum | E28: 45385 | F28: 3178 | G28: priya.7024@auroraliving.com | H28: N/A | I28: Inactive
A29: AU-7025 | B29: PETER BROWN | C29: Boston | D29: Platinum | E29: 45118 | F29: 1011 | G29: peter.7025@auroraliving.com | H29: +1-555-499-2439 | I29: Inactive
A30: AU-7026 | B30: grace wong | C30: Austin | D30: Gold | E30: 45324 | F30: 3452 | G30: grace7026auroralivingcom | H30: N/A | I30: Active

Sheet Question 4
A1: AURORA PHARMACY & WELLNESS — Product Inventory & Order Log | Used for: Q4 | N1: QUESTION 4 — [10 Marks]
N2: Business Context: Aurora Pharmacy & Wellness's Procurement Manager needs to quickly retrieve product and supplier details using product codes, and wants to plan a promotional stock order for the upcoming Wellness Fair that maximises profit within budget and storage limits.
A4: PRODUCT MASTER TABLE | H4: SUPPLIER REFERENCE | N4: (a) [2 pts] | O4: CLO1 | U4: Score:
A5: ProductCode | B5: Product Name | C5: Category | D5: Unit Cost | E5: Selling Price | F5: Stock Qty | H5: SupplierCode | I5: Supplier Name | J5: Lead Days | K5: Region | N5: On a new sheet named 'Q4_Lookups', create an input cell labelled 'Product Code:' (e.g., PW-V001). Using VLOOKUP with IFERROR, retrieve the Product Name, Category, and Selling Price from the Product Master Table. Display 'Code Not Found' if the product code does not exist.
A6: PW-M001 | B6: Pain Relief Tablets 500mg | C6: Medicines | D6: 2 | E6: 5.99 | F6: 320 | H6: SP-01 | I6: MediSource Global | J6: 7 | K6: Asia
A7: PW-M002 | B7: Cold & Flu Syrup | C7: Medicines | D7: 3.5 | E7: 8.99 | F7: 150 | H7: SP-02 | I7: WellCare Distributors | J7: 5 | K7: North America | N7: (b) [3 pts] | O7: CLO1 | U7: Score:
A8: PW-M003 | B8: Antacid Tablets | C8: Medicines | D8: 1.8 | E8: 4.49 | F8: 275 | H8: SP-03 | I8: PharmaLink Ltd | J8: 10 | K8: Europe | N8: Create a two-way lookup using INDEX with MATCH functions. Use one input cell for Product Code (row lookup against Product Master) and a second input cell for a column header name (e.g. 'Selling Price' or 'Stock Qty'). The formula should return the value at the intersection of the matched row and matched column — dynamically, without hardcoding column numbers.
A9: PW-V001 | B9: Vitamin C 1000mg (60ct) | C9: Vitamins | D9: 4 | E9: 9.99 | F9: 210 | H9: SP-04 | I9: HealthPlus Supply | J9: 4 | K9: Local
A10: PW-V002 | B10: Multivitamin Daily | C10: Vitamins | D10: 6 | E10: 14.99 | F10: 180 | N10: (c) [5 pts] | O10: CLO3 | U10: Score:
A11: PW-V003 | B11: Omega-3 Fish Oil | C11: Vitamins | D11: 7.5 | E11: 17.99 | F11: 140 | N11: SOLVER PROBLEM — For the upcoming Wellness Fair, Aurora Pharmacy & Wellness has a promotional budget of $2,000 to order extra units of two fast-moving products: Vitamin C 1000mg (Unit Cost $4.00, Selling Price $9.99) and Multivitamin Daily (Unit Cost $6.00, Selling Price $14.99). The stockroom can hold at most 300 combined extra units. On a new sheet named 'Q4_Solver', set up: (1) two Variable cells — Extra Vitamin C Units and Extra Multivitamin Units; (2) Total Profit = (Selling Price - Unit Cost) x Units, summed for both products; (3) a Budget Used cell (=SUMPRODUCT of Unit Cost and Units cells) (4) Constraints: Total Units can be maximum of 300; Budget must not exceed $2,000; Both product units must be greater than 0. Use Solver to Maximise the Total Profit cell by changing number of units, subject to the constraints above. State the optimal number of units of each product and the maximum profit achieved.
A12: PW-D001 | B12: Digital Thermometer | C12: Medical Devices | D12: 8 | E12: 19.99 | F12: 65
A13: PW-D002 | B13: Blood Pressure Monitor | C13: Medical Devices | D13: 35 | E13: 79.99 | F13: 40
A14: PW-D003 | B14: Pulse Oximeter | C14: Medical Devices | D14: 15 | E14: 34.99 | F14: 58
A15: PW-C001 | B15: Hand Sanitizer 500ml | C15: Personal Care | D15: 2.5 | E15: 6.49 | F15: 400
A16: PW-C002 | B16: Face Masks (50pk) | C16: Personal Care | D16: 5 | E16: 12.99 | F16: 300
A17: PW-C003 | B17: First Aid Kit | C17: Personal Care | D17: 12 | E17: 27.99 | F17: 95
A20: ORDER LOG
A21: OrderID | B21: OrderDate | C21: ProductCode | D21: SupplierCode | E21: Qty Ordered | F21: Unit Cost | G21: Total Cost | H21: Expected Delivery | I21: Status | J21: CustomerType | K21: Priority
A22: ORD-4001 | B22: 2024-01-03 | C22: PW-V002 | D22: SP-01 | E22: 7 | F22: 6 | G22: 42 | H22: 2024-01-15 | I22: In Transit | J22: Wholesale | K22: Normal
A23: ORD-4002 | B23: 2024-01-11 | C23: PW-M003 | D23: SP-02 | E23: 39 | F23: 1.8 | G23: 70.2 | H23: 2024-01-21 | I23: Delivered | J23: Corporate | K23: Low
A24: ORD-4003 | B24: 2024-01-21 | C24: PW-M001 | D24: SP-01 | E24: 15 | F24: 2 | G24: 30 | H24: 2024-02-04 | I24: Cancelled | J24: Wholesale | K24: High
A25: ORD-4004 | B25: 2024-01-30 | C25: PW-V003 | D25: SP-01 | E25: 31 | F25: 7.5 | G25: 232.5 | H25: 2024-02-14 | I25: Delivered | J25: Retail | K25: Normal
A26: ORD-4005 | B26: 2024-02-04 | C26: PW-C001 | D26: SP-02 | E26: 99 | F26: 2.5 | G26: 247.5 | H26: 2024-02-12 | I26: In Transit | J26: Retail | K26: Normal
A27: ORD-4006 | B27: 2024-02-12 | C27: PW-C001 | D27: SP-01 | E27: 109 | F27: 2.5 | G27: 272.5 | H27: 2024-02-22 | I27: Pending | J27: Retail | K27: Normal
A28: ORD-4007 | B28: 2024-02-22 | C28: PW-C002 | D28: SP-02 | E28: 28 | F28: 5 | G28: 140 | H28: 2024-03-08 | I28: Pending | J28: Retail | K28: Normal
A29: ORD-4008 | B29: 2024-02-28 | C29: PW-C001 | D29: SP-01 | E29: 15 | F29: 2.5 | G29: 37.5 | H29: 2024-03-03 | I29: Cancelled | J29: Corporate | K29: Low
A30: ORD-4009 | B30: 2024-03-06 | C30: PW-C001 | D30: SP-03 | E30: 110 | F30: 2.5 | G30: 275 | H30: 2024-03-18 | I30: In Transit | J30: Corporate | K30: Normal
A31: ORD-4010 | B31: 2024-03-13 | C31: PW-D003 | D31: SP-03 | E31: 104 | F31: 15 | G31: 1560 | H31: 2024-03-23 | I31: Pending | J31: Wholesale | K31: High
A32: ORD-4011 | B32: 2024-03-17 | C32: PW-C001 | D32: SP-01 | E32: 95 | F32: 2.5 | G32: 237.5 | H32: 2024-04-01 | I32: Cancelled | J32: Corporate | K32: Normal
A33: ORD-4012 | B33: 2024-03-22 | C33: PW-C003 | D33: SP-01 | E33: 54 | F33: 12 | G33: 648 | H33: 2024-03-27 | I33: Cancelled | J33: Corporate | K33: High
... A71: ORD-4050 | B71: 2024-12-12 | C71: PW-V003 | D71: SP-01 | E71: 33 | F71: 7.5 | G71: 247.5 | H71: 2024-12-27 | I71: Pending | J71: Corporate | K71: Low

Sheet Question 5
A1: AURORA PHARMACY & WELLNESS — Product Inventory & Order Log | Used for: Q5 | N1: QUESTION 5 — [10 Marks]
N2: Business Context: Aurora Pharmacy & Wellness's Supply Chain team needs an automated order classification and risk-flagging system built directly in Excel. Using the Order Log and Product Master tables, write logical formulas that categorise orders, flag supply risks, assign reorder priorities, and identify high-value deals — without manual input or helper lookup formulas beyond basic referencing.
A4: PRODUCT MASTER TABLE | H4: SUPPLIER REFERENCE | N4: (a) [2 pts] | O4: CLO1 | U4: Score:
A5: ProductCode | B5: Product Name | C5: Category | D5: Unit Cost | E5: Selling Price | F5: Stock Qty | H5: SupplierCode | I5: Supplier Name | J5: Lead Days | K5: Region | N5: On a new sheet named 'Q5_Logic', copy the Order Log (50 rows + headers). Add a column 'Order Category'. Label each order if the Qty Ordered is greater than or equal to 50 then Medium, otherwise Small.
A6: PW-M001 | B6: Pain Relief Tablets 500mg | C6: Medicines | D6: 2 | E6: 5.99 | F6: 320 | H6: SP-01 | I6: MediSource Global | J6: 7 | K6: Asia
A7: PW-M002 | B7: Cold & Flu Syrup | C7: Medicines | D7: 3.5 | E7: 8.99 | F7: 150 | H7: SP-02 | I7: WellCare Distributors | J7: 5 | K7: North America | N7: (b) [2 pts] | O7: CLO1 | U7: Score:
A8: PW-M003 | B8: Antacid Tablets | C8: Medicines | D8: 1.8 | E8: 4.49 | F8: 275 | H8: SP-03 | I8: PharmaLink Ltd | J8: 10 | K8: Europe | N8: Add a column 'Rush Flag', if priority is high or status is pending then label as ‘Rush’, for the rest display ‘Standard’
A9: PW-V001 | B9: Vitamin C 1000mg (60ct) | C9: Vitamins | D9: 4 | E9: 9.99 | F9: 210 | H9: SP-04 | I9: HealthPlus Supply | J9: 4 | K9: Local
A10: PW-V002 | B10: Multivitamin Daily | C10: Vitamins | D10: 6 | E10: 14.99 | F10: 180 | N10: (c) [2 pts] | O10: CLO1 | U10: Score:
A11: PW-V003 | B11: Omega-3 Fish Oil | C11: Vitamins | D11: 7.5 | E11: 17.99 | F11: 140 | N11: Add a column 'Approved'. An order is 'Approved' only if ALL of the following are true: Status is NOT 'Cancelled', Qty Ordered is greater than 0, and CustomerType is either 'Corporate' or 'Wholesale'. Otherwise display 'Rejected'. Use a single formula.
A12: PW-D001 | B12: Digital Thermometer | C12: Medical Devices | D12: 8 | E12: 19.99 | F12: 65
A13: PW-D002 | B13: Blood Pressure Monitor | C13: Medical Devices | D13: 35 | E13: 79.99 | F13: 40 | N13: (d) [2 pts] | O13: CLO1 | U13: Score:
A14: PW-D003 | B14: Pulse Oximeter | C14: Medical Devices | D14: 15 | E14: 34.99 | F14: 58 | N14: Add a column 'Cost Tier'. Classify Total Cost as: 'Premium' if Total Cost is greater than 1000 ; 'Standard' if Total Cost is less than 1000 and greater than 200, 'Economy' if Total Cost is above 0, and 'No Cost' for anything else.
A15: PW-C001 | B15: Hand Sanitizer 500ml | C15: Personal Care | D15: 2.5 | E15: 6.49 | F15: 400
A16: PW-C002 | B16: Face Masks (50pk) | C16: Personal Care | D16: 5 | E16: 12.99 | F16: 300 | N16: (e) [2 pts] | O16: CLO1 | U16: Score:
A17: PW-C003 | B17: First Aid Kit | C17: Personal Care | D17: 12 | E17: 27.99 | F17: 95 | N17: Add a column 'Reorder Alert'. Flag an order as 'Alert — Review Needed' if the order status is NOT 'Delivered' and the order is NOT labelled 'Small' ; Otherwise display 'No Action'. Use NOT() explicitly in your formula.
A20: ORDER LOG
A21: OrderID | B21: OrderDate | C21: ProductCode | D21: SupplierCode | E21: Qty Ordered | F21: Unit Cost | G21: Total Cost | H21: Expected Delivery | I21: Status | J21: CustomerType | K21: Priority
A22: ORD-4001 | B22: 2024-01-03 | C22: PW-V002 | D22: SP-01 | E22: 7 | F22: 6 | G22: 42 | H22: 2024-01-15 | I22: In Transit | J22: Wholesale | K22: Normal
A23: ORD-4002 | B23: 2024-01-11 | C23: PW-M003 | D23: SP-02 | E23: 39 | F23: 1.8 | G23: 70.2 | H23: 2024-01-21 | I23: Delivered | J23: Corporate | K23: Low
A24: ORD-4003 | B24: 2024-01-21 | C24: PW-M001 | D24: SP-01 | E24: 15 | F24: 2 | G24: 30 | H24: 2024-02-04 | I24: Cancelled | J24: Wholesale | K24: High
A25: ORD-4004 | B25: 2024-01-30 | C25: PW-V003 | D25: SP-01 | E25: 31 | F25: 7.5 | G25: 232.5 | H25: 2024-02-14 | I25: Delivered | J25: Retail | K25: Normal
A26: ORD-4005 | B26: 2024-02-04 | C26: PW-C001 | D26: SP-02 | E26: 99 | F26: 2.5 | G26: 247.5 | H26: 2024-02-12 | I26: In Transit | J26: Retail | K26: Normal
A27: ORD-4006 | B27: 2024-02-12 | C27: PW-C001 | D27: SP-01 | E27: 109 | F27: 2.5 | G27: 272.5 | H27: 2024-02-22 | I27: Pending | J27: Retail | K27: Normal
A28: ORD-4007 | B28: 2024-02-22 | C28: PW-C002 | D28: SP-02 | E28: 28 | F28: 5 | G28: 140 | H28: 2024-03-08 | I28: Pending | J28: Retail | K28: Normal
A29: ORD-4008 | B29: 2024-02-28 | C29: PW-C001 | D29: SP-01 | E29: 15 | F29: 2.5 | G29: 37.5 | H29: 2024-03-03 | I29: Cancelled | J29: Corporate | K29: Low
A30: ORD-4009 | B30: 2024-03-06 | C30: PW-C001 | D30: SP-03 | E30: 110 | F30: 2.5 | G30: 275 | H30: 2024-03-18 | I30: In Transit | J30: Corporate | K30: Normal
A31: ORD-4010 | B31: 2024-03-13 | C31: PW-D003 | D31: SP-03 | E31: 104 | F31: 15 | G31: 1560 | H31: 2024-03-23 | I31: Pending | J31: Wholesale | K31: High
A32: ORD-4011 | B32: 2024-03-17 | C32: PW-C001 | D32: SP-01 | E32: 95 | F32: 2.5 | G32: 237.5 | H32: 2024-04-01 | I32: Cancelled | J32: Corporate | K32: Normal
A33: ORD-4012 | B33: 2024-03-22 | C33: PW-C003 | D33: SP-01 | E33: 54 | F33: 12 | G33: 648 | H33: 2024-03-27 | I33: Cancelled | J33: Corporate | K33: High
... A71: ORD-4050 | B71: 2024-12-12 | C71: PW-V003 | D71: SP-01 | E71: 33 | F71: 7.5 | G71: 247.5 | H71: 2024-12-27 | I71: Pending | J71: Corporate | K71: Low

Sheet Q5_Logic
L1: Order Category | M1: Rush Flag | N1: Approved | O1: Cost Tier | P1: Reorder Alert
A2: ORDER LOG | L2: =IF(E2>=50, "Medium", "Small") | M2: =IF(OR(K2="High", I2="Pending"), "Rush", "Standard") | N2: =IF(AND(I2<>"Cancelled", E2>0, OR(J2="Corporate", J2="Wholesale")), "Approved", "Rejected") | O2: =IFS(G2>1000, "Premium", AND(G2<1000, G2>200), "Standard", G2>0, "Economy", TRUE, "No Cost") | P2: =IF(AND(NOT(I2="Delivered"), NOT(L2="Small")), "Alert — Review Needed", "No Action")
A3: OrderID | B3: OrderDate | C3: ProductCode | D3: SupplierCode | E3: Qty Ordered | F3: Unit Cost | G3: Total Cost | H3: Expected Delivery | I3: Status | J3: CustomerType | K3: Priority | L3: =IF(E3>=50, "Medium", "Small") | M3: =IF(OR(K3="High", I3="Pending"), "Rush", "Standard") | N3: =IF(AND(I3<>"Cancelled", E3>0, OR(J3="Corporate", J3="Wholesale")), "Approved", "Rejected") | O3: =IFS(G3>1000, "Premium", AND(G3<1000, G3>200), "Standard", G3>0, "Economy", TRUE, "No Cost") | P3: =IF(AND(NOT(I3="Delivered"), NOT(L3="Small")), "Alert — Review Needed", "No Action")
A4: ORD-4001 | B4: 2024-01-03 | C4: PW-V002 | D4: SP-01 | E4: 7 | F4: 6 | G4: 42 | H4: 2024-01-15 | I4: In Transit | J4: Wholesale | K4: Normal | L4: =IF(E4>=50, "Medium", "Small") | M4: =IF(OR(K4="High", I4="Pending"), "Rush", "Standard") | N4: =IF(AND(I4<>"Cancelled", E4>0, OR(J4="Corporate", J4="Wholesale")), "Approved", "Rejected") | O4: =IFS(G4>1000, "Premium", AND(G4<1000, G4>200), "Standard", G4>0, "Economy", TRUE, "No Cost") | P4: =IF(AND(NOT(I4="Delivered"), NOT(L4="Small")), "Alert — Review Needed", "No Action")
A5: ORD-4002 | B5: 2024-01-11 | C5: PW-M003 | D5: SP-02 | E5: 39 | F5: 1.8 | G5: 70.2 | H5: 2024-01-21 | I5: Delivered | J5: Corporate | K5: Low | L5: =IF(E5>=50, "Medium", "Small") | M5: =IF(OR(K5="High", I5="Pending"), "Rush", "Standard") | N5: =IF(AND(I5<>"Cancelled", E5>0, OR(J5="Corporate", J5="Wholesale")), "Approved", "Rejected") | O5: =IFS(G5>1000, "Premium", AND(G5<1000, G5>200), "Standard", G5>0, "Economy", TRUE, "No Cost") | P5: =IF(AND(NOT(I5="Delivered"), NOT(L5="Small")), "Alert — Review Needed", "No Action")
A6: ORD-4003 | B6: 2024-01-21 | C6: PW-M001 | D6: SP-01 | E6: 15 | F6: 2 | G6: 30 | H6: 2024-02-04 | I6: Cancelled | J6: Wholesale | K6: High | L6: =IF(E6>=50, "Medium", "Small") | M6: =IF(OR(K6="High", I6="Pending"), "Rush", "Standard") | N6: =IF(AND(I6<>"Cancelled", E6>0, OR(J6="Corporate", J6="Wholesale")), "Approved", "Rejected") | O6: =IFS(G6>1000, "Premium", AND(G6<1000, G6>200), "Standard", G6>0, "Economy", TRUE, "No Cost") | P6: =IF(AND(NOT(I6="Delivered"), NOT(L6="Small")), "Alert — Review Needed", "No Action")
A7: ORD-4004 | B7: 2024-01-30 | C7: PW-V003 | D7: SP-01 | E7: 31 | F7: 7.5 | G7: 232.5 | H7: 2024-02-14 | I7: Delivered | J7: Retail | K7: Normal | L7: =IF(E7>=50, "Medium", "Small") | M7: =IF(OR(K7="High", I7="Pending"), "Rush", "Standard") | N7: =IF(AND(I7<>"Cancelled", E7>0, OR(J7="Corporate", J7="Wholesale")), "Approved", "Rejected") | O7: =IFS(G7>1000, "Premium", AND(G7<1000, G7>200), "Standard", G7>0, "Economy", TRUE, "No Cost") | P7: =IF(AND(NOT(I7="Delivered"), NOT(L7="Small")), "Alert — Review Needed", "No Action")
A8: ORD-4005 | B8: 2024-02-04 | C8: PW-C001 | D8: SP-02 | E8: 99 | F8: 2.5 | G8: 247.5 | H8: 2024-02-12 | I8: In Transit | J8: Retail | K8: Normal | L8: =IF(E8>=50, "Medium", "Small") | M8: =IF(OR(K8="High", I8="Pending"), "Rush", "Standard") | N8: =IF(AND(I8<>"Cancelled", E8>0, OR(J8="Corporate", J8="Wholesale")), "Approved", "Rejected") | O8: =IFS(G8>1000, "Premium", AND(G8<1000, G8>200), "Standard", G8>0, "Economy", TRUE, "No Cost") | P8: =IF(AND(NOT(I8="Delivered"), NOT(L8="Small")), "Alert — Review Needed", "No Action")
A9: ORD-4006 | B9: 2024-02-12 | C9: PW-C001 | D9: SP-01 | E9: 109 | F9: 2.5 | G9: 272.5 | H9: 2024-02-22 | I9: Pending | J9: Retail | K9: Normal | L9: =IF(E9>=50, "Medium", "Small") | M9: =IF(OR(K9="High", I9="Pending"), "Rush", "Standard") | N9: =IF(AND(I9<>"Cancelled", E9>0, OR(J9="Corporate", J9="Wholesale")), "Approved", "Rejected") | O9: =IFS(G9>1000, "Premium", AND(G9<1000, G9>200), "Standard", G9>0, "Economy", TRUE, "No Cost") | P9: =IF(AND(NOT(I9="Delivered"), NOT(L9="Small")), "Alert — Review Needed", "No Action")
A10: ORD-4007 | B10: 2024-02-22 | C10: PW-C002 | D10: SP-02 | E10: 28 | F10: 5 | G10: 140 | H10: 2024-03-08 | I10: Pending | J10: Retail | K10: Normal | L10: =IF(E10>=50, "Medium", "Small") | M10: =IF(OR(K10="High", I10="Pending"), "Rush", "Standard") | N10: =IF(AND(I10<>"Cancelled", E10>0, OR(J10="Corporate", J10="Wholesale")), "Approved", "Rejected") | O10: =IFS(G10>1000, "Premium", AND(G10<1000, G10>200), "Standard", G10>0, "Economy", TRUE, "No Cost") | P10: =IF(AND(NOT(I10="Delivered"), NOT(L10="Small")), "Alert — Review Needed", "No Action")
A11: ORD-4008 | B11: 2024-02-28 | C11: PW-C001 | D11: SP-01 | E11: 15 | F11: 2.5 | G11: 37.5 | H11: 2024-03-03 | I11: Cancelled | J11: Corporate | K11: Low | L11: =IF(E11>=50, "Medium", "Small") | M11: =IF(OR(K11="High", I11="Pending"), "Rush", "Standard") | N11: =IF(AND(I11<>"Cancelled", E11>0, OR(J11="Corporate", J11="Wholesale")), "Approved", "Rejected") | O11: =IFS(G11>1000, "Premium", AND(G11<1000, G11>200), "Standard", G11>0, "Economy", TRUE, "No Cost") | P11: =IF(AND(NOT(I11="Delivered"), NOT(L11="Small")), "Alert — Review Needed", "No Action")
A12: ORD-4009 | B12: 2024-03-06 | C12: PW-C001 | D12: SP-03 | E12: 110 | F12: 2.5 | G12: 275 | H12: 2024-03-18 | I12: In Transit | J12: Corporate | K12: Normal | L12: =IF(E12>=50, "Medium", "Small") | M12: =IF(OR(K12="High", I12="Pending"), "Rush", "Standard") | N12: =IF(AND(I12<>"Cancelled", E12>0, OR(J12="Corporate", J12="Wholesale")), "Approved", "Rejected") | O12: =IFS(G12>1000, "Premium", AND(G12<1000, G12>200), "Standard", G12>0, "Economy", TRUE, "No Cost") | P12: =IF(AND(NOT(I12="Delivered"), NOT(L12="Small")), "Alert — Review Needed", "No Action")
A13: ORD-4010 | B13: 2024-03-13 | C13: PW-D003 | D13: SP-03 | E13: 104 | F13: 15 | G13: 1560 | H13: 2024-03-23 | I13: Pending | J13: Wholesale | K13: High | L13: =IF(E13>=50, "Medium", "Small") | M13: =IF(OR(K13="High", I13="Pending"), "Rush", "Standard") | N13: =IF(AND(I13<>"Cancelled", E13>0, OR(J13="Corporate", J13="Wholesale")), "Approved", "Rejected") | O13: =IFS(G13>1000, "Premium", AND(G13<1000, G13>200), "Standard", G13>0, "Economy", TRUE, "No Cost") | P13: =IF(AND(NOT(I13="Delivered"), NOT(L13="Small")), "Alert — Review Needed", "No Action")
A14: ORD-4011 | B14: 2024-03-17 | C14: PW-C001 | D14: SP-01 | E14: 95 | F14: 2.5 | G14: 237.5 | H14: 2024-04-01 | I14: Cancelled | J14: Corporate | K14: Normal | L14: =IF(E14>=50, "Medium", "Small") | M14: =IF(OR(K14="High", I14="Pending"), "Rush", "Standard") | N14: =IF(AND(I14<>"Cancelled", E14>0, OR(J14="Corporate", J14="Wholesale")), "Approved", "Rejected") | O14: =IFS(G14>1000, "Premium", AND(G14<1000, G14>200), "Standard", G14>0, "Economy", TRUE, "No Cost") | P14: =IF(AND(NOT(I14="Delivered"), NOT(L14="Small")), "Alert — Review Needed", "No Action")
A15: ORD-4012 | B15: 2024-03-22 | C15: PW-C003 | D15: SP-01 | E15: 54 | F15: 12 | G15: 648 | H15: 2024-03-27 | I15: Cancelled | J15: Corporate | K15: High | L15: =IF(E15>=50, "Medium", "Small") | M15: =IF(OR(K15="High", I15="Pending"), "Rush", "Standard") | N15: =IF(AND(I15<>"Cancelled", E15>0, OR(J15="Corporate", J15="Wholesale")), "Approved", "Rejected") | O15: =IFS(G15>1000, "Premium", AND(G15<1000, G15>200), "Standard", G15>0, "Economy", TRUE, "No Cost") | P15: =IF(AND(NOT(I15="Delivered"), NOT(L15="Small")), "Alert — Review Needed", "No Action")
... A51: ORD-4048 | B51: 2024-11-29 | C51: PW-M002 | D51: SP-01 | E51: 101 | F51: 3.5 | G51: 353.5 | H51: 2024-12-10 | I51: Pending | J51: Retail | K51: Low | L51: =IF(E51>=50, "Medium", "Small") | M51: =IF(OR(K51="High", I51="Pending"), "Rush", "Standard") | N51: =IF(AND(I51<>"Cancelled", E51>0, OR(J51="Corporate", J51="Wholesale")), "Approved", "Rejected") | O51: =IFS(G51>1000, "Premium", AND(G51<1000, G51>200), "Standard", G51>0, "Economy", TRUE, "No Cost") | P51: =IF(AND(NOT(I51="Delivered"), NOT(L51="Small")), "Alert — Review Needed", "No Action")

Sheet Q4_Lookups
A1: Product Code: | B1: PW-V001 | D1: INDEX/MATCH Two-Way Lookup
A3: VLOOKUP Results: | D3: Product Code: | E3: PW-M002
A4: Product Name | B4: =IFERROR(VLOOKUP(B1, 'Question 4'!$A$5:$K$14, 2, FALSE), "Code Not Found") | D4: Column Header: | E4: Stock Qty
A5: Category | B5: =IFERROR(VLOOKUP(B1, 'Question 4'!$A$5:$K$14, 3, FALSE), "Code Not Found")
A6: Selling Price | B6: =IFERROR(VLOOKUP(B1, 'Question 4'!$A$5:$K$14, 5, FALSE), "Code Not Found") | D6: Result: | E6: =INDEX('Question 4'!$A$5:$K$14, MATCH(E3, 'Question 4'!$A$5:$A$14, 0), MATCH(E4, 'Question 4'!$A$4:$K$4, 0))

Sheet Q4_Solver
A1: Aurora Pharmacy Solver Model
A3: Product | B3: Unit Cost | C3: Selling Price | D3: Profit/Unit | E3: Extra Units to Order
A4: Vitamin C 1000mg | B4: 4 | C4: 9.99 | D4: =C4-B4 | E4: 0
A5: Multivitamin Daily | B5: 6 | C5: 14.99 | D5: =C5-B5 | E5: 0
A7: Total Units | B7: =SUM(E4:E5)
A8: Budget Used | B8: =SUMPRODUCT(B4:B5, E4:E5)
A9: Total Profit | B9: =SUMPRODUCT(D4:D5, E4:E5)
A11: Constraints
A12: Max Units | B12: 300
A13: Max Budget | B13: 2000

Sheet Q2_WhatIf
A1: SunGuard Skincare Co. - Monthly Revenue Model
A3: Key Inputs
A4: Selling price per unit | B4: ='Question 2'!B3
A5: Variable cost per unit | B5: ='Question 2'!B4
A6: Base units sold per month | B6: ='Question 2'!B5
A7: Fixed costs per month | B7: ='Question 2'!B6
A8: Tax rate | B8: ='Question 2'!B7
A10: Variable Assumptions
A11: Units Increase % | B11: 0
A12: Price Change % | B12: 0
A14: Operating Results
A15: Units Sold | B15: =B5 * (1 + B10)
A16: Selling price per unit | B16: =B3 * (1 + B11)
A17: Revenue | B17: =B14 * B15
A18: Variable Costs | B18: =B4 * B14
A19: Fixed Costs | B19: =B6
A20: Total Costs | B20: =B17 + B18
A21: Gross Profit | B21: =B16 - B19
A22: Taxes | B22: =IF(B20>0, B20*B7, 0)
A23: Net Profit | B23: =B20 - B21
A25: Data Table: Projected Net Profit (Rows: Units Increase %, Columns: Price Change %)
A26: =B22 | B26: -0.2 | C26: -0.1 | D26: 0 | E26: 0.1 | F26: 0.2
A27: 0
A28: 0.05
A29: 0.1
A30: 0.15
A31: 0.2
A32: 0.25
A33: 0.3
A35: Break-Even Sales Volume: | B35: =B6 / (B15 - B4)
A37: Interpretation:
A38: The Data Table indicates that Net Profit is highly sensitive to Price changes. A decrease in price (-10% or -20%) quickly leads to negative profit unless offset by a massive, unrealistic volume increase. Conversely, raising the price (+10% or +20%) exponentially increases Net Profit even if units sold remains static (0%).

Sheet Q3_Clean
A1: CustomerID | B1: Full Name | C1: City | D1: Membership Tier | E1: Join Date | F1: Points Balance | G1: Email | H1: Phone | I1: Status | J1: Cleaned Name | K1: Cleaned Phone | L1: Cleaned Join Date
A2: AU-7001 | B2: LIAM BIANCHI | C2: Portland | D2: Silver | E2: 44820 | F2: 771 | G2: liam.7001auroraliving.com | H2: 555-3323 | I2: Active | J2: =PROPER(TRIM('Question 3'!B5)) | K2: =IF(LEN(SUBSTITUTE(SUBSTITUTE(SUBSTITUTE(SUBSTITUTE('Question 3'!H5, "-", ""), "+", ""), "(", ""), ")", ""))<11, "Invalid", "+1-(" & MID(SUBSTITUTE(SUBSTITUTE(SUBSTITUTE(SUBSTITUTE('Question 3'!H5, "-", ""), "+", ""), "(", ""), ")", ""), 2, 3) & ")-" & MID(SUBSTITUTE(SUBSTITUTE(SUBSTITUTE(SUBSTITUTE('Question 3'!H5, "-", ""), "+", ""), "(", ""), ")", ""), 5, 3) & "-" & RIGHT(SUBSTITUTE(SUBSTITUTE(SUBSTITUTE(SUBSTITUTE('Question 3'!H5, "-", ""), "+", ""), "(", ""), ")", ""), 4)) | L2: =TEXT('Question 3'!E5, "dd-mmm-yyyy") | N2: Data Clean Summary
A3: AU-7002 | B3: Grace Patel | C3: Phoenix | D3: Platinum | E3: 45646 | F3: 4328 | G3: grace.7002@auroraliving.com | H3: 555-136-4116 | I3: Active | J3: =PROPER(TRIM('Question 3'!B6)) | K3: =IF(LEN(SUBSTITUTE(SUBSTITUTE(SUBSTITUTE(SUBSTITUTE('Question 3'!H6, "-", ""), "+", ""), "(", ""), ")", ""))<11, "Invalid", "+1-(" & MID(SUBSTITUTE(SUBSTITUTE(SUBSTITUTE(SUBSTITUTE('Question 3'!H6, "-", ""), "+", ""), "(", ""), ")", ""), 2, 3) & ")-" & MID(SUBSTITUTE(SUBSTITUTE(SUBSTITUTE(SUBSTITUTE('Question 3'!H6, "-", ""), "+", ""), "(", ""), ")", ""), 5, 3) & "-" & RIGHT(SUBSTITUTE(SUBSTITUTE(SUBSTITUTE(SUBSTITUTE('Question 3'!H6, "-", ""), "+", ""), "(", ""), ")", ""), 4)) | L3: =TEXT('Question 3'!E6, "dd-mmm-yyyy") | N3: Task (b): Used =PROPER(TRIM(cell)) to fix inconsistent casing and remove extra/leading spaces.
A4: AU-7003 | B4: AMINA BROWN | C4: Boston | D4: Platinum | E4: 45399 | F4: 4094 | G4: amina.7003@auroraliving.com | H4: 555-568-5557 | I4: Inactive | J4: =PROPER(TRIM('Question 3'!B7)) | K4: =IF(LEN(SUBSTITUTE(SUBSTITUTE(SUBSTITUTE(SUBSTITUTE('Question 3'!H7, "-", ""), "+", ""), "(", ""), ")", ""))<11, "Invalid", "+1-(" & MID(SUBSTITUTE(SUBSTITUTE(SUBSTITUTE(SUBSTITUTE('Question 3'!H7, "-", ""), "+", ""), "(", ""), ")", ""), 2, 3) & ")-" & MID(SUBSTITUTE(SUBSTITUTE(SUBSTITUTE(SUBSTITUTE('Question 3'!H7, "-", ""), "+", ""), "(", ""), ")", ""), 5, 3) & "-" & RIGHT(SUBSTITUTE(SUBSTITUTE(SUBSTITUTE(SUBSTITUTE('Question 3'!H7, "-", ""), "+", ""), "(", ""), ")", ""), 4)) | L4: =TEXT('Question 3'!E7, "dd-mmm-yyyy") | N4: Task (c): Used nested SUBSTITUTE to remove symbols, checked length with LEN, and concatenated with formatting.
A5: AU-7004 | B5: Grace Clarke | C5: Chicago | D5: Gold | E5: 44843 | G5: grace.7004@auroraliving.com | H5: N/A | I5: Active | J5: =PROPER(TRIM('Question 3'!B8)) | K5: =IF(LEN(SUBSTITUTE(SUBSTITUTE(SUBSTITUTE(SUBSTITUTE('Question 3'!H8, "-", ""), "+", ""), "(", ""), ")", ""))<11, "Invalid", "+1-(" & MID(SUBSTITUTE(SUBSTITUTE(SUBSTITUTE(SUBSTITUTE('Question 3'!H8, "-", ""), "+", ""), "(", ""), ")", ""), 2, 3) & ")-" & MID(SUBSTITUTE(SUBSTITUTE(SUBSTITUTE(SUBSTITUTE('Question 3'!H8, "-", ""), "+", ""), "(", ""), ")", ""), 5, 3) & "-" & RIGHT(SUBSTITUTE(SUBSTITUTE(SUBSTITUTE(SUBSTITUTE('Question 3'!H8, "-", ""), "+", ""), "(", ""), ")", ""), 4)) | L5: =TEXT('Question 3'!E8, "dd-mmm-yyyy") | N5: Task (d): Used =TEXT(cell, "dd-mmm-yyyy") to standardize date formats into a uniform text string.
A6: AU-7005 | B6: Maria Hassan | C6: Austin | D6: Bronze | E6: 44653 | F6: 3255 | G6: maria.7005auroraliving.com | H6: 555-679-4252 | I6: Suspended | J6: =PROPER(TRIM('Question 3'!B9)) | K6: =IF(LEN(SUBSTITUTE(SUBSTITUTE(SUBSTITUTE(SUBSTITUTE('Question 3'!H9, "-", ""), "+", ""), "(", ""), ")", ""))<11, "Invalid", "+1-(" & MID(SUBSTITUTE(SUBSTITUTE(SUBSTITUTE(SUBSTITUTE('Question 3'!H9, "-", ""), "+", ""), "(", ""), ")", ""), 2, 3) & ")-" & MID(SUBSTITUTE(SUBSTITUTE(SUBSTITUTE(SUBSTITUTE('Question 3'!H9, "-", ""), "+", ""), "(", ""), ")", ""), 5, 3) & "-" & RIGHT(SUBSTITUTE(SUBSTITUTE(SUBSTITUTE(SUBSTITUTE('Question 3'!H9, "-", ""), "+", ""), "(", ""), ")", ""), 4)) | L6: =TEXT('Question 3'!E9, "dd-mmm-yyyy")
A7: AU-7006 | B7: David Wong | C7: Chicago | D7: Gold | E7: 44767 | F7: -411 | G7: david.7006@auroraliving.com | H7: 555-161-8617 | I7: Inactive | J7: =PROPER(TRIM('Question 3'!B10)) | K7: =IF(LEN(SUBSTITUTE(SUBSTITUTE(SUBSTITUTE(SUBSTITUTE('Question 3'!H10, "-", ""), "+", ""), "(", ""), ")", ""))<11, "Invalid", "+1-(" & MID(SUBSTITUTE(SUBSTITUTE(SUBSTITUTE(SUBSTITUTE('Question 3'!H10, "-", ""), "+", ""), "(", ""), ")", ""), 2, 3) & ")-" & MID(SUBSTITUTE(SUBSTITUTE(SUBSTITUTE(SUBSTITUTE('Question 3'!H10, "-", ""), "+", ""), "(", ""), ")", ""), 5, 3) & "-" & RIGHT(SUBSTITUTE(SUBSTITUTE(SUBSTITUTE(SUBSTITUTE('Question 3'!H10, "-", ""), "+", ""), "(", ""), ")", ""), 4)) | L7: =TEXT('Question 3'!E10, "dd-mmm-yyyy")
A8: AU-7007 | B8: Fatima Bianchi | C8: Portland | D8: Silver | E8: 45365 | F8: -265 | G8: fatima.7007@auroraliving.com | H8: 555-376-5983 | I8: Active | J8: =PROPER(TRIM('Question 3'!B11)) | K8: =IF(LEN(SUBSTITUTE(SUBSTITUTE(SUBSTITUTE(SUBSTITUTE('Question 3'!H11, "-", ""), "+", ""), "(", ""), ")", ""))<11, "Invalid", "+1-(" & MID(SUBSTITUTE(SUBSTITUTE(SUBSTITUTE(SUBSTITUTE('Question 3'!H11, "-", ""), "+", ""), "(", ""), ")", ""), 2, 3) & ")-" & MID(SUBSTITUTE(SUBSTITUTE(SUBSTITUTE(SUBSTITUTE('Question 3'!H11, "-", ""), "+", ""), "(", ""), ")", ""), 5, 3) & "-" & RIGHT(SUBSTITUTE(SUBSTITUTE(SUBSTITUTE(SUBSTITUTE('Question 3'!H11, "-", ""), "+", ""), "(", ""), ")", ""), 4)) | L8: =TEXT('Question 3'!E11, "dd-mmm-yyyy")
A9: AU-7008 | B9: PETER MALIK | C9: Denver | D9: Bronze | E9: 44666 | H9: 555-5854 | I9: Inactive | J9: =PROPER(TRIM('Question 3'!B12)) | K9: =IF(LEN(SUBSTITUTE(SUBSTITUTE(SUBSTITUTE(SUBSTITUTE('Question 3'!H12, "-", ""), "+", ""), "(", ""), ")", ""))<11, "Invalid", "+1-(" & MID(SUBSTITUTE(SUBSTITUTE(SUBSTITUTE(SUBSTITUTE('Question 3'!H12, "-", ""), "+", ""), "(", ""), ")", ""), 2, 3) & ")-" & MID(SUBSTITUTE(SUBSTITUTE(SUBSTITUTE(SUBSTITUTE('Question 3'!H12, "-", ""), "+", ""), "(", ""), ")", ""), 5, 3) & "-" & RIGHT(SUBSTITUTE(SUBSTITUTE(SUBSTITUTE(SUBSTITUTE('Question 3'!H12, "-", ""), "+", ""), "(", ""), ")", ""), 4)) | L9: =TEXT('Question 3'!E12, "dd-mmm-yyyy")
A10: AU-7009 | B10: Tom Clarke | C10: Miami | D10: Silver | E10: 44846 | F10: 1042 | H10: N/A | I10: Suspended | J10: =PROPER(TRIM('Question 3'!B13)) | K10: =IF(LEN(SUBSTITUTE(SUBSTITUTE(SUBSTITUTE(SUBSTITUTE('Question 3'!H13, "-", ""), "+", ""), "(", ""), ")", ""))<11, "Invalid", "+1-(" & MID(SUBSTITUTE(SUBSTITUTE(SUBSTITUTE(SUBSTITUTE('Question 3'!H13, "-", ""), "+", ""), "(", ""), ")", ""), 2, 3) & ")-" & MID(SUBSTITUTE(SUBSTITUTE(SUBSTITUTE(SUBSTITUTE('Question 3'!H13, "-", ""), "+", ""), "(", ""), ")", ""), 5, 3) & "-" & RIGHT(SUBSTITUTE(SUBSTITUTE(SUBSTITUTE(SUBSTITUTE('Question 3'!H13, "-", ""), "+", ""), "(", ""), ")", ""), 4)) | L10: =TEXT('Question 3'!E13, "dd-mmm-yyyy")
A11: AU-7010 | B11: James Hassan | C11: Seattle | D11: Gold | E11: 44842 | F11: -372 | H11: +1-555-803-7360 | I11: Inactive | J11: =PROPER(TRIM('Question 3'!B14)) | K11: =IF(LEN(SUBSTITUTE(SUBSTITUTE(SUBSTITUTE(SUBSTITUTE('Question 3'!H14, "-", ""), "+", ""), "(", ""), ")", ""))<11, "Invalid", "+1-(" & MID(SUBSTITUTE(SUBSTITUTE(SUBSTITUTE(SUBSTITUTE('Question 3'!H14, "-", ""), "+", ""), "(", ""), ")", ""), 2, 3) & ")-" & MID(SUBSTITUTE(SUBSTITUTE(SUBSTITUTE(SUBSTITUTE('Question 3'!H14, "-", ""), "+", ""), "(", ""), ")", ""), 5, 3) & "-" & RIGHT(SUBSTITUTE(SUBSTITUTE(SUBSTITUTE(SUBSTITUTE('Question 3'!H14, "-", ""), "+", ""), "(", ""), ")", ""), 4)) | L11: =TEXT('Question 3'!E14, "dd-mmm-yyyy")
A12: AU-7011 | B12: AMINA CLARKE | C12: Austin | D12: Bronze | E12: 44578 | F12: 3208 | G12: amina7011auroralivingcom | H12: N/A | I12: Suspended | J12: =PROPER(TRIM('Question 3'!B15)) | K12: =IF(LEN(SUBSTITUTE(SUBSTITUTE(SUBSTITUTE(SUBSTITUTE('Question 3'!H15, "-", ""), "+", ""), "(", ""), ")", ""))<11, "Invalid", "+1-(" & MID(SUBSTITUTE(SUBSTITUTE(SUBSTITUTE(SUBSTITUTE('Question 3'!H15, "-", ""), "+", ""), "(", ""), ")", ""), 2, 3) & ")-" & MID(SUBSTITUTE(SUBSTITUTE(SUBSTITUTE(SUBSTITUTE('Question 3'!H15, "-", ""), "+", ""), "(", ""), ")", ""), 5, 3) & "-" & RIGHT(SUBSTITUTE(SUBSTITUTE(SUBSTITUTE(SUBSTITUTE('Question 3'!H15, "-", ""), "+", ""), "(", ""), ")", ""), 4)) | L12: =TEXT('Question 3'!E15, "dd-mmm-yyyy")
A13: AU-7012 | B13: Zainab Garcia | C13: Seattle | D13: Bronze | E13: 44667 | F13: 607 | G13: zainab7012auroralivingcom | H13: +1-555-308-1271 | I13: Active | J13: =PROPER(TRIM('Question 3'!B16)) | K13: =IF(LEN(SUBSTITUTE(SUBSTITUTE(SUBSTITUTE(SUBSTITUTE('Question 3'!H16, "-", ""), "+", ""), "(", ""), ")", ""))<11, "Invalid", "+1-(" & MID(SUBSTITUTE(SUBSTITUTE(SUBSTITUTE(SUBSTITUTE('Question 3'!H16, "-", ""), "+", ""), "(", ""), ")", ""), 2, 3) & ")-" & MID(SUBSTITUTE(SUBSTITUTE(SUBSTITUTE(SUBSTITUTE('Question 3'!H16, "-", ""), "+", ""), "(", ""), ")", ""), 5, 3) & "-" & RIGHT(SUBSTITUTE(SUBSTITUTE(SUBSTITUTE(SUBSTITUTE('Question 3'!H16, "-", ""), "+", ""), "(", ""), ")", ""), 4)) | L13: =TEXT('Question 3'!E16, "dd-mmm-yyyy")
A14: AU-7013 | B14: DAVID ROSSI | C14: Miami | D14: Bronze | E14: 44630 | F14: 1077 | G14: david.7013@auroraliving.com | H14: 555-3267 | I14: Inactive | J14: =PROPER(TRIM('Question 3'!B17)) | K14: =IF(LEN(SUBSTITUTE(SUBSTITUTE(SUBSTITUTE(SUBSTITUTE('Question 3'!H17, "-", ""), "+", ""), "(", ""), ")", ""))<11, "Invalid", "+1-(" & MID(SUBSTITUTE(SUBSTITUTE(SUBSTITUTE(SUBSTITUTE('Question 3'!H17, "-", ""), "+", ""), "(", ""), ")", ""), 2, 3) & ")-" & MID(SUBSTITUTE(SUBSTITUTE(SUBSTITUTE(SUBSTITUTE('Question 3'!H17, "-", ""), "+", ""), "(", ""), ")", ""), 5, 3) & "-" & RIGHT(SUBSTITUTE(SUBSTITUTE(SUBSTITUTE(SUBSTITUTE('Question 3'!H17, "-", ""), "+", ""), "(", ""), ")", ""), 4)) | L14: =TEXT('Question 3'!E17, "dd-mmm-yyyy")
A15: AU-7014 | B15: Chen Torres | C15: Seattle | D15: Bronze | E15: 44785 | F15: 174 | H15: 555-593-2102 | I15: Suspended | J15: =PROPER(TRIM('Question 3'!B18)) | K15: =IF(LEN(SUBSTITUTE(SUBSTITUTE(SUBSTITUTE(SUBSTITUTE('Question 3'!H18, "-", ""), "+", ""), "(", ""), ")", ""))<11, "Invalid", "+1-(" & MID(SUBSTITUTE(SUBSTITUTE(SUBSTITUTE(SUBSTITUTE('Question 3'!H18, "-", ""), "+", ""), "(", ""), ")", ""), 2, 3) & ")-" & MID(SUBSTITUTE(SUBSTITUTE(SUBSTITUTE(SUBSTITUTE('Question 3'!H18, "-", ""), "+", ""), "(", ""), ")", ""), 5, 3) & "-" & RIGHT(SUBSTITUTE(SUBSTITUTE(SUBSTITUTE(SUBSTITUTE('Question 3'!H18, "-", ""), "+", ""), "(", ""), ")", ""), 4)) | L15: =TEXT('Question 3'!E18, "dd-mmm-yyyy")
A16: AU-7015 | B16: Maria Wong | C16: Denver | D16: Bronze | E16: 45269 | F16: 1061 | G16: maria7015auroralivingcom | H16: 555-2391 | I16: Suspended | J16: =PROPER(TRIM('Question 3'!B19)) | K16: =IF(LEN(SUBSTITUTE(SUBSTITUTE(SUBSTITUTE(SUBSTITUTE('Question 3'!H19, "-", ""), "+", ""), "(", ""), ")", ""))<11, "Invalid", "+1-(" & MID(SUBSTITUTE(SUBSTITUTE(SUBSTITUTE(SUBSTITUTE('Question 3'!H19, "-", ""), "+", ""), "(", ""), ")", ""), 2, 3) & ")-" & MID(SUBSTITUTE(SUBSTITUTE(SUBSTITUTE(SUBSTITUTE('Question 3'!H19, "-", ""), "+", ""), "(", ""), ")", ""), 5, 3) & "-" & RIGHT(SUBSTITUTE(SUBSTITUTE(SUBSTITUTE(SUBSTITUTE('Question 3'!H19, "-", ""), "+", ""), "(", ""), ")", ""), 4)) | L16: =TEXT('Question 3'!E19, "dd-mmm-yyyy")
A17: AU-7016 | B17: ZAINAB CLARKE | C17: Austin | D17: Platinum | E17: 45311 | F17: 101 | H17: 555-182-2485 | I17: Suspended | J17: =PROPER(TRIM('Question 3'!B20)) | K17: =IF(LEN(SUBSTITUTE(SUBSTITUTE(SUBSTITUTE(SUBSTITUTE('Question 3'!H20, "-", ""), "+", ""), "(", ""), ")", ""))<11, "Invalid", "+1-(" & MID(SUBSTITUTE(SUBSTITUTE(SUBSTITUTE(SUBSTITUTE('Question 3'!H20, "-", ""), "+", ""), "(", ""), ")", ""), 2, 3) & ")-" & MID(SUBSTITUTE(SUBSTITUTE(SUBSTITUTE(SUBSTITUTE('Question 3'!H20, "-", ""), "+", ""), "(", ""), ")", ""), 5, 3) & "-" & RIGHT(SUBSTITUTE(SUBSTITUTE(SUBSTITUTE(SUBSTITUTE('Question 3'!H20, "-", ""), "+", ""), "(", ""), ")", ""), 4)) | L17: =TEXT('Question 3'!E20, "dd-mmm-yyyy")
A18: AU-7017 | B18: LINDA NGUYEN | C18: Boston | D18: Platinum | E18: 45645 | F18: 4433 | G18: linda.7017@auroraliving.com | H18: 555-417-2437 | I18: Inactive | J18: =PROPER(TRIM('Question 3'!B21)) | K18: =IF(LEN(SUBSTITUTE(SUBSTITUTE(SUBSTITUTE(SUBSTITUTE('Question 3'!H21, "-", ""), "+", ""), "(", ""), ")", ""))<11, "Invalid", "+1-(" & MID(SUBSTITUTE(SUBSTITUTE(SUBSTITUTE(SUBSTITUTE('Question 3'!H21, "-", ""), "+", ""), "(", ""), ")", ""), 2, 3) & ")-" & MID(SUBSTITUTE(SUBSTITUTE(SUBSTITUTE(SUBSTITUTE('Question 3'!H21, "-", ""), "+", ""), "(", ""), ")", ""), 5, 3) & "-" & RIGHT(SUBSTITUTE(SUBSTITUTE(SUBSTITUTE(SUBSTITUTE('Question 3'!H21, "-", ""), "+", ""), "(", ""), ")", ""), 4)) | L18: =TEXT('Question 3'!E21, "dd-mmm-yyyy")
A19: AU-7018 | B19: Michael Johnson | C19: Denver | D19: Platinum | E19: 45612 | F19: 3014 | G19: michael7018auroralivingcom | H19: +1-555-794-4318 | I19: Suspended | J19: =PROPER(TRIM('Question 3'!B22)) | K19: =IF(LEN(SUBSTITUTE(SUBSTITUTE(SUBSTITUTE(SUBSTITUTE('Question 3'!H22, "-", ""), "+", ""), "(", ""), ")", ""))<11, "Invalid", "+1-(" & MID(SUBSTITUTE(SUBSTITUTE(SUBSTITUTE(SUBSTITUTE('Question 3'!H22, "-", ""), "+", ""), "(", ""), ")", ""), 2, 3) & ")-" & MID(SUBSTITUTE(SUBSTITUTE(SUBSTITUTE(SUBSTITUTE('Question 3'!H22, "-", ""), "+", ""), "(", ""), ")", ""), 5, 3) & "-" & RIGHT(SUBSTITUTE(SUBSTITUTE(SUBSTITUTE(SUBSTITUTE('Question 3'!H22, "-", ""), "+", ""), "(", ""), ")", ""), 4)) | L19: =TEXT('Question 3'!E22, "dd-mmm-yyyy")
A20: AU-7019 | B20: Fatima Wong | C20: Portland | D20: Platinum | E20: 44725 | F20: 3529 | G20: fatima.7019@auroraliving.com | H20: +1-555-493-4597 | I20: Suspended | J20: =PROPER(TRIM('Question 3'!B23)) | K20: =IF(LEN(SUBSTITUTE(SUBSTITUTE(SUBSTITUTE(SUBSTITUTE('Question 3'!H23, "-", ""), "+", ""), "(", ""), ")", ""))<11, "Invalid", "+1-(" & MID(SUBSTITUTE(SUBSTITUTE(SUBSTITUTE(SUBSTITUTE('Question 3'!H23, "-", ""), "+", ""), "(", ""), ")", ""), 2, 3) & ")-" & MID(SUBSTITUTE(SUBSTITUTE(SUBSTITUTE(SUBSTITUTE('Question 3'!H23, "-", ""), "+", ""), "(", ""), ")", ""), 5, 3) & "-" & RIGHT(SUBSTITUTE(SUBSTITUTE(SUBSTITUTE(SUBSTITUTE('Question 3'!H23, "-", ""), "+", ""), "(", ""), ")", ""), 4)) | L20: =TEXT('Question 3'!E23, "dd-mmm-yyyy")
A21: AU-7020 | B21: Chen Adams | C21: Seattle | D21: Platinum | E21: 45314 | F21: 2267 | G21: chen.7020@auroraliving.com | H21: 555-561-8722 | I21: Inactive | J21: =PROPER(TRIM('Question 3'!B24)) | K21: =IF(LEN(SUBSTITUTE(SUBSTITUTE(SUBSTITUTE(SUBSTITUTE('Question 3'!H24, "-", ""), "+", ""), "(", ""), ")", ""))<11, "Invalid", "+1-(" & MID(SUBSTITUTE(SUBSTITUTE(SUBSTITUTE(SUBSTITUTE('Question 3'!H24, "-", ""), "+", ""), "(", ""), ")", ""), 2, 3) & ")-" & MID(SUBSTITUTE(SUBSTITUTE(SUBSTITUTE(SUBSTITUTE('Question 3'!H24, "-", ""), "+", ""), "(", ""), ")", ""), 5, 3) & "-" & RIGHT(SUBSTITUTE(SUBSTITUTE(SUBSTITUTE(SUBSTITUTE('Question 3'!H24, "-", ""), "+", ""), "(", ""), ")", ""), 4)) | L21: =TEXT('Question 3'!E24, "dd-mmm-yyyy")
A22: AU-7021 | B22: PETER ROSSI | C22: Portland | D22: Gold | E22: 45580 | G22: peter.7021@auroraliving.com | H22: 555-1679 | I22: Suspended | J22: =PROPER(TRIM('Question 3'!B25)) | K22: =IF(LEN(SUBSTITUTE(SUBSTITUTE(SUBSTITUTE(SUBSTITUTE('Question 3'!H25, "-", ""), "+", ""), "(", ""), ")", ""))<11, "Invalid", "+1-(" & MID(SUBSTITUTE(SUBSTITUTE(SUBSTITUTE(SUBSTITUTE('Question 3'!H25, "-", ""), "+", ""), "(", ""), ")", ""), 2, 3) & ")-" & MID(SUBSTITUTE(SUBSTITUTE(SUBSTITUTE(SUBSTITUTE('Question 3'!H25, "-", ""), "+", ""), "(", ""), ")", ""), 5, 3) & "-" & RIGHT(SUBSTITUTE(SUBSTITUTE(SUBSTITUTE(SUBSTITUTE('Question 3'!H25, "-", ""), "+", ""), "(", ""), ")", ""), 4)) | L22: =TEXT('Question 3'!E25, "dd-mmm-yyyy")
A23: AU-7022 | B23: david cohen | C23: Chicago | D23: Bronze | E23: 45364 | F23: 2182 | G23: david.7022@auroraliving.com | H23: +1-555-915-1769 | I23: Suspended | J23: =PROPER(TRIM('Question 3'!B26)) | K23: =IF(LEN(SUBSTITUTE(SUBSTITUTE(SUBSTITUTE(SUBSTITUTE('Question 3'!H26, "-", ""), "+", ""), "(", ""), ")", ""))<11, "Invalid", "+1-(" & MID(SUBSTITUTE(SUBSTITUTE(SUBSTITUTE(SUBSTITUTE('Question 3'!H26, "-", ""), "+", ""), "(", ""), ")", ""), 2, 3) & ")-" & MID(SUBSTITUTE(SUBSTITUTE(SUBSTITUTE(SUBSTITUTE('Question 3'!H26, "-", ""), "+", ""), "(", ""), ")", ""), 5, 3) & "-" & RIGHT(SUBSTITUTE(SUBSTITUTE(SUBSTITUTE(SUBSTITUTE('Question 3'!H26, "-", ""), "+", ""), "(", ""), ")", ""), 4)) | L23: =TEXT('Question 3'!E26, "dd-mmm-yyyy")
A24: AU-7023 | B24: Linda Murphy | C24: Boston | D24: Bronze | E24: 45389 | F24: 88 | G24: linda.7023auroraliving.com | H24: 555-283-4710 | I24: Inactive | J24: =PROPER(TRIM('Question 3'!B27)) | K24: =IF(LEN(SUBSTITUTE(SUBSTITUTE(SUBSTITUTE(SUBSTITUTE('Question 3'!H27, "-", ""), "+", ""), "(", ""), ")", ""))<11, "Invalid", "+1-(" & MID(SUBSTITUTE(SUBSTITUTE(SUBSTITUTE(SUBSTITUTE('Question 3'!H27, "-", ""), "+", ""), "(", ""), ")", ""), 2, 3) & ")-" & MID(SUBSTITUTE(SUBSTITUTE(SUBSTITUTE(SUBSTITUTE('Question 3'!H27, "-", ""), "+", ""), "(", ""), ")", ""), 5, 3) & "-" & RIGHT(SUBSTITUTE(SUBSTITUTE(SUBSTITUTE(SUBSTITUTE('Question 3'!H27, "-", ""), "+", ""), "(", ""), ")", ""), 4)) | L24: =TEXT('Question 3'!E27, "dd-mmm-yyyy")
A25: AU-7024 | B25: Priya Bianchi | C25: Seattle | D25: Platinum | E25: 45385 | F25: 3178 | G25: priya.7024@auroraliving.com | H25: N/A | I25: Inactive | J25: =PROPER(TRIM('Question 3'!B28)) | K25: =IF(LEN(SUBSTITUTE(SUBSTITUTE(SUBSTITUTE(SUBSTITUTE('Question 3'!H28, "-", ""), "+", ""), "(", ""), ")", ""))<11, "Invalid", "+1-(" & MID(SUBSTITUTE(SUBSTITUTE(SUBSTITUTE(SUBSTITUTE('Question 3'!H28, "-", ""), "+", ""), "(", ""), ")", ""), 2, 3) & ")-" & MID(SUBSTITUTE(SUBSTITUTE(SUBSTITUTE(SUBSTITUTE('Question 3'!H28, "-", ""), "+", ""), "(", ""), ")", ""), 5, 3) & "-" & RIGHT(SUBSTITUTE(SUBSTITUTE(SUBSTITUTE(SUBSTITUTE('Question 3'!H28, "-", ""), "+", ""), "(", ""), ")", ""), 4)) | L25: =TEXT('Question 3'!E28, "dd-mmm-yyyy")
A26: AU-7025 | B26: PETER BROWN | C26: Boston | D26: Platinum | E26: 45118 | F26: 1011 | G26: peter.7025@auroraliving.com | H26: +1-555-499-2439 | I26: Inactive | J26: =PROPER(TRIM('Question 3'!B29)) | K26: =IF(LEN(SUBSTITUTE(SUBSTITUTE(SUBSTITUTE(SUBSTITUTE('Question 3'!H29, "-", ""), "+", ""), "(", ""), ")", ""))<11, "Invalid", "+1-(" & MID(SUBSTITUTE(SUBSTITUTE(SUBSTITUTE(SUBSTITUTE('Question 3'!H29, "-", ""), "+", ""), "(", ""), ")", ""), 2, 3) & ")-" & MID(SUBSTITUTE(SUBSTITUTE(SUBSTITUTE(SUBSTITUTE('Question 3'!H29, "-", ""), "+", ""), "(", ""), ")", ""), 5, 3) & "-" & RIGHT(SUBSTITUTE(SUBSTITUTE(SUBSTITUTE(SUBSTITUTE('Question 3'!H29, "-", ""), "+", ""), "(", ""), ")", ""), 4)) | L26: =TEXT('Question 3'!E29, "dd-mmm-yyyy")
A27: AU-7026 | B27: grace wong | C27: Austin | D27: Gold | E27: 45324 | F27: 3452 | G27: grace7026auroralivingcom | H27: N/A | I27: Active | J27: =PROPER(TRIM('Question 3'!B30)) | K27: =IF(LEN(SUBSTITUTE(SUBSTITUTE(SUBSTITUTE(SUBSTITUTE('Question 3'!H30, "-", ""), "+", ""), "(", ""), ")", ""))<11, "Invalid", "+1-(" & MID(SUBSTITUTE(SUBSTITUTE(SUBSTITUTE(SUBSTITUTE('Question 3'!H30, "-", ""), "+", ""), "(", ""), ")", ""), 2, 3) & ")-" & MID(SUBSTITUTE(SUBSTITUTE(SUBSTITUTE(SUBSTITUTE('Question 3'!H30, "-", ""), "+", ""), "(", ""), ")", ""), 5, 3) & "-" & RIGHT(SUBSTITUTE(SUBSTITUTE(SUBSTITUTE(SUBSTITUTE('Question 3'!H30, "-", ""), "+", ""), "(", ""), ")", ""), 4)) | L27: =TEXT('Question 3'!E30, "dd-mmm-yyyy")
